hunabku_index/__init__.py
hunabku_index/_version.py
hunabku_index/endpoints/Index.py
Hunabku_index-0.0.1a0.dist-info/METADATA
Hunabku_index-0.0.1a0.dist-info/WHEEL
Hunabku_index-0.0.1a0.dist-info/top_level.txt
Hunabku_index-0.0.1a0.dist-info/RECORD
