Metadata-Version: 2.1
Name: Hunabku-index
Version: 0.0.1a0
Summary: Hunabku plguin to redirect the index
Home-page: https://github.com/colav/Hunabku_plugins
Author: Colav
Author-email: colav@udea.edu.co
License: BSD
Requires-Dist: flask (>=1.1.2)
Requires-Dist: requests (>=2.22.0)
Requires-Dist: hunabku
